vibium_win32_x64/__init__.py
vibium_win32_x64/bin/clicker.exe
vibium_win32_x64-0.1.4.dist-info/METADATA
vibium_win32_x64-0.1.4.dist-info/WHEEL
vibium_win32_x64-0.1.4.dist-info/licenses/LICENSE
vibium_win32_x64-0.1.4.dist-info/licenses/NOTICE
vibium_win32_x64-0.1.4.dist-info/RECORD
